hypha_launcher/__init__.py
hypha_launcher/__main__.py
hypha_launcher/api.py
hypha_launcher/constants.py
hypha_launcher/utils/__init__.py
hypha_launcher/utils/container.py
hypha_launcher/utils/download.py
hypha_launcher/utils/hpc.py
hypha_launcher/utils/log.py
hypha_launcher/utils/misc.py
hypha_launcher-0.1.3.dist-info/LICENSE
hypha_launcher-0.1.3.dist-info/METADATA
hypha_launcher-0.1.3.dist-info/WHEEL
hypha_launcher-0.1.3.dist-info/top_level.txt
hypha_launcher-0.1.3.dist-info/RECORD
