Metadata-Version: 2.1
Name: hypha-launcher
Version: 0.1.3
Summary: Launcher for hypha services
Author-email: Weize Xu <vet.xwz@gmail.com>, Wei Ouyang <oeway007@gmail.com>
License-File: LICENSE
Requires-Dist: aiohttp
Requires-Dist: requests
Requires-Dist: tqdm
Requires-Dist: fire
Requires-Dist: loguru
Requires-Dist: executor-engine
Requires-Dist: hypha
Requires-Dist: uvicorn
Requires-Dist: imjoy-rpc
Requires-Dist: pyotritonclient
Requires-Dist: psutil
